redisboard/__init__.py
redisboard/__main__.py
redisboard/admin.py
redisboard/apps.py
redisboard/cli.py
redisboard/conf.py
redisboard/connection.py
redisboard/data.py
redisboard/models.py
redisboard/structs.py
redisboard/utils.py
redisboard/migrations/0001_initial.py
redisboard/migrations/0002_add_url.py
redisboard/migrations/0003_fill_url.py
redisboard/migrations/0004_cleanup.py
redisboard/migrations/0005_config.py
redisboard/migrations/__init__.py
redisboard/static/redisboard/admin.css
redisboard/static/redisboard/favicon.ico
redisboard/templates/admin/redisboard/redisserver/change_form.html
redisboard/templates/admin/redisboard/redisserver/change_list.html
redisboard/templates/admin/redisboard/redisserver/details_display.html
redisboard/templates/redisboard/details.html
redisboard/templates/redisboard/inspect.html
redisboard/templates/redisboard/inspect_key.html
django_redisboard-8.4.0.dist-info/AUTHORS.rst
django_redisboard-8.4.0.dist-info/LICENSE
django_redisboard-8.4.0.dist-info/METADATA
django_redisboard-8.4.0.dist-info/WHEEL
django_redisboard-8.4.0.dist-info/entry_points.txt
django_redisboard-8.4.0.dist-info/top_level.txt
django_redisboard-8.4.0.dist-info/RECORD
